Module_hello_word/__init__.py
Module_hello_word/One_son_Module/__init__.py
Module_hello_word/One_son_Module/Two_son_Module/__init__.py
Module_hello_word/One_son_Module/Two_son_Module/Three_son_Module/__init__.py
Module_hello_word/One_son_Module/Two_son_Module/Three_son_Module/hello.py
Module_hello_word/One_son_Module/Two_son_Module/Three_son_Module/lql.py
HELLO_WORLD_LQL-1.0.1.dist-info/METADATA
HELLO_WORLD_LQL-1.0.1.dist-info/WHEEL
HELLO_WORLD_LQL-1.0.1.dist-info/top_level.txt
HELLO_WORLD_LQL-1.0.1.dist-info/RECORD
