Metadata-Version: 2.1
Name: HELLO-WORLD-LQL
Version: 1.0.1
Summary: 你好，世界！！
Home-page: http://www.XXXXX.com
Author: 刘青路
License: UNKNOWN
Platform: UNKNOWN
